galaxies/__init__.py
galaxies/main.py
galaxies/res/global_variables.json
galaxies/res/logo_lip6.gif
galaxies/res/logo_sorbonne.gif
galaxies/res/sql/create_galaxie.sql
galaxies/src/__init__.py
galaxies/src/common/__init__.py
galaxies/src/common/file.py
galaxies/src/common/maths.py
galaxies/src/core/__init__.py
galaxies/src/core/amas.py
galaxies/src/core/community.py
galaxies/src/core/database_tools.py
galaxies/src/core/environment.py
galaxies/src/core/extraction_galaxies.py
galaxies/src/core/extraction_galaxies_new.py
galaxies/src/core/graphe_galaxies.py
galaxies/src/core/interface.py
galaxies/src/core/parser.py
galaxies/src/getters/__init__.py
galaxies/src/getters/environment.py
galaxies/src/getters/get_global_variable.py
galaxies/src/gui/__init__.py
galaxies/src/gui/galaxie_creation.py
galaxies/src/gui/galaxie_vizualisation.py
galaxies/src/gui/gtk_tab_bas.py
galaxies/src/gui/gtk_tab_filtres.py
galaxies/src/gui/gtk_tab_inside.py
galaxies/src/gui/gui_tools.py
galaxies/src/gui/main_menu.py
galaxies/test/__init__.py
galaxies/test/gui.py
galaxies/test/test_graphe.py
galaxies-1.0.0.dist-info/METADATA
galaxies-1.0.0.dist-info/RECORD
galaxies-1.0.0.dist-info/WHEEL
galaxies-1.0.0.dist-info/entry_points.txt
galaxies-1.0.0.dist-info/top_level.txt
