Metadata-Version: 2.1
Name: galaxies
Version: 1.0.0
Summary: [fr] GUI & CLI for reuse aggregates' visualization 
Home-page: https://github.com/NicolasBizzozzero/galaxies
Author: BizzozzÃ©ro Nicolas, Adoum Robert
Author-email: nicolasbizzozzero@gmail.com
License: GPL-3.0
Download-URL: https://github.com/NicolasBizzozzero/galaxies/tarball/master
Keywords: gui,cli,vizualisation,reuses
Platform: UNKNOWN
Classifier: Development Status :: 5 - Production/Stable
Classifier: Natural Language :: French
Classifier: Intended Audience :: Science/Research
Classifier: Topic :: Scientific/Engineering :: Visualization
Classifier: License :: OSI Approved :: GNU General Public License v3 (GPLv3)
Classifier: Programming Language :: Python :: 3.5
Requires-Dist: click (>=6.7)
Requires-Dist: progressbar33 (>=2.4)
Requires-Dist: networkx (>=2.1)
